et/__about__.py
et/__init__.py
et/destruct.py
et/fixtures.py
et/nget.py
et/service.py
et/utc_now.py
ether_utils-0.2.0.dist-info/METADATA
ether_utils-0.2.0.dist-info/WHEEL
ether_utils-0.2.0.dist-info/entry_points.txt
ether_utils-0.2.0.dist-info/licenses/LICENSE
ether_utils-0.2.0.dist-info/RECORD
