Metadata-Version: 2.4
Name: ether-utils
Version: 0.2.0
Summary: Python utilities for better development.
Project-URL: Documentation, https://github.com/tavor118/ether#readme
Project-URL: Issues, https://github.com/tavor118/ether/issues
Project-URL: Source, https://github.com/tavor118/ether
License-Expression: MIT
License-File: LICENSE
Keywords: functional,service,utility
Classifier: Framework :: Pytest
Classifier: Programming Language :: Python
Classifier: Programming Language :: Python :: 3.9
Classifier: Programming Language :: Python :: 3.10
Classifier: Programming Language :: Python :: 3.11
Classifier: Programming Language :: Python :: 3.12
Classifier: Topic :: Software Development :: Libraries
Classifier: Topic :: Software Development :: Libraries :: Python Modules
Classifier: Topic :: Utilities
Requires-Python: >=3.9
